{
  "version": 1,
  "kind": "phase-handoff",
  "phase": "202",
  "step": "execute",
  "status": "complete",
  "run_id": "202-2026-04-07T00-47-56-158Z",
  "source_fingerprint": "dbd425be606db7a8",
  "created_at": "2026-04-07T01:04:46.619Z",
  "updated_at": "2026-04-07T01:04:46.619Z",
  "summary": "Execution complete for Phase 202",
  "resume_target": {
    "phase": "202",
    "step": "execute",
    "plan": null,
    "resume_file": null,
    "next_command": "/bgsd-verify-work 202"
  },
  "context": {}
}
